craft_platforms/__init__.py
craft_platforms/_architectures.py
craft_platforms/_build.py
craft_platforms/_buildinfo.py
craft_platforms/_distro.py
craft_platforms/_errors.py
craft_platforms/_platforms.py
craft_platforms/_utils.py
craft_platforms/_version.py
craft_platforms/py.typed
craft_platforms/charm/__init__.py
craft_platforms/charm/_build.py
craft_platforms/rock/__init__.py
craft_platforms/rock/_build.py
craft_platforms/snap/__init__.py
craft_platforms/snap/_build.py
craft_platforms/test/__init__.py
craft_platforms/test/strategies.py
craft_platforms-0.10.0.dist-info/licenses/LICENSE
craft_platforms-0.10.0.dist-info/METADATA
craft_platforms-0.10.0.dist-info/WHEEL
craft_platforms-0.10.0.dist-info/top_level.txt
craft_platforms-0.10.0.dist-info/RECORD
